GDriveUtils/__init__.py
GDriveUtils/config.py
GDriveUtils/gdrive_file_handler.py
GDU-0.1.dist-info/LICENSE.txt
GDU-0.1.dist-info/METADATA
GDU-0.1.dist-info/WHEEL
GDU-0.1.dist-info/entry_points.txt
GDU-0.1.dist-info/top_level.txt
GDU-0.1.dist-info/RECORD
