Metadata-Version: 2.1
Name: GDU
Version: 0.1
Summary: G-Drive Utils
Home-page: 
Author: Max Buehler
License: MIT
Keywords: python
Classifier: Development Status :: 4 - Beta
Classifier: Intended Audience :: Developers
Classifier: License :: OSI Approved :: MIT License
Classifier: Programming Language :: Python
Classifier: Programming Language :: Python :: 3
Classifier: Programming Language :: Python :: 3 :: Only
Classifier: Programming Language :: Python :: 3.7
Requires-Python: >=3.8
License-File: LICENSE.txt
Requires-Dist: numpy
Requires-Dist: pyzmq
Requires-Dist: pydrive2
Requires-Dist: oauth2client
